<annotation>
	<folder>jpegImages</folder>
	<filename>252.jpg</filename>
	<path>C:\Qurantine\Web Scrapping\jpegImages\252.jpg</path>
	<source>
		<database>Unknown</database>
	</source>
	<size>
		<width>1000</width>
		<height>1432</height>
		<depth>3</depth>
	</size>
	<segmented>0</segmented>
	<object>
		<name>Mask</name>
		<pose>Unspecified</pose>
		<truncated>0</truncated>
		<difficult>0</difficult>
		<bndbox>
			<xmin>420</xmin>
			<ymin>470</ymin>
			<xmax>689</xmax>
			<ymax>706</ymax>
		</bndbox>
	</object>
</annotation>
