<annotation>
	<folder>jpegImages</folder>
	<filename>337.jpg</filename>
	<path>C:\Qurantine\Web Scrapping\jpegImages\337.jpg</path>
	<source>
		<database>Unknown</database>
	</source>
	<size>
		<width>715</width>
		<height>574</height>
		<depth>3</depth>
	</size>
	<segmented>0</segmented>
	<object>
		<name>Mask</name>
		<pose>Unspecified</pose>
		<truncated>0</truncated>
		<difficult>0</difficult>
		<bndbox>
			<xmin>240</xmin>
			<ymin>160</ymin>
			<xmax>360</xmax>
			<ymax>270</ymax>
		</bndbox>
	</object>
</annotation>
