<annotation>
	<folder>jpegImages</folder>
	<filename>426.jpg</filename>
	<path>C:\Qurantine\Web Scrapping\jpegImages\426.jpg</path>
	<source>
		<database>Unknown</database>
	</source>
	<size>
		<width>216</width>
		<height>233</height>
		<depth>3</depth>
	</size>
	<segmented>0</segmented>
	<object>
		<name>Mask</name>
		<pose>Unspecified</pose>
		<truncated>0</truncated>
		<difficult>0</difficult>
		<bndbox>
			<xmin>30</xmin>
			<ymin>119</ymin>
			<xmax>157</xmax>
			<ymax>199</ymax>
		</bndbox>
	</object>
</annotation>
