<annotation>
	<folder>jpegImages</folder>
	<filename>454.jpg</filename>
	<path>C:\Qurantine\Web Scrapping\jpegImages\454.jpg</path>
	<source>
		<database>Unknown</database>
	</source>
	<size>
		<width>225</width>
		<height>225</height>
		<depth>3</depth>
	</size>
	<segmented>0</segmented>
	<object>
		<name>Mask</name>
		<pose>Unspecified</pose>
		<truncated>0</truncated>
		<difficult>0</difficult>
		<bndbox>
			<xmin>56</xmin>
			<ymin>95</ymin>
			<xmax>134</xmax>
			<ymax>169</ymax>
		</bndbox>
	</object>
</annotation>
