<annotation>
	<folder>jpegImages</folder>
	<filename>460.jpg</filename>
	<path>C:\Qurantine\Web Scrapping\jpegImages\460.jpg</path>
	<source>
		<database>Unknown</database>
	</source>
	<size>
		<width>651</width>
		<height>651</height>
		<depth>3</depth>
	</size>
	<segmented>0</segmented>
	<object>
		<name>Mask</name>
		<pose>Unspecified</pose>
		<truncated>0</truncated>
		<difficult>0</difficult>
		<bndbox>
			<xmin>186</xmin>
			<ymin>327</ymin>
			<xmax>453</xmax>
			<ymax>513</ymax>
		</bndbox>
	</object>
</annotation>
